Metadata-Version: 1.2
Name: pyascii
Version: 0.0.3
Summary: A tool for converting images or videos to ASCII.
Home-page: https://github.com/zhoudaxia233/PyAscii
License: MIT
Keywords: asciiart
Platform: UNKNOWN
Requires-Python: >=3.6
